MANIFEST.in
README.md
setup.py
RESOURCES/.suffix
RESOURCES/dummy
node_configure/__init__.py
node_configure/args_parser.py
node_configure/bin.py
node_configure/configure.py
node_configure/exec.py
node_configure/getmoduleversion.py
node_configure/getnapibuildversion.py
node_configure/gyp_node.py
node_configure/nodedownload.py
node_configure/util.py
node_configure.egg-info/PKG-INFO
node_configure.egg-info/SOURCES.txt
node_configure.egg-info/dependency_links.txt
node_configure.egg-info/entry_points.txt
node_configure.egg-info/top_level.txt